reportmix/__init__.py
reportmix/__main__.py
reportmix/errors.py
reportmix/exporter.py
reportmix/loader.py
reportmix/main.py
reportmix/mixer.py
reportmix/config/__init__.py
reportmix/config/builder.py
reportmix/config/property.py
reportmix/exporters/__init__.py
reportmix/exporters/csv.py
reportmix/exporters/html.py
reportmix/exporters/json.py
reportmix/exporters/templates/reportmix.html.jinja2
reportmix/loaders/__init__.py
reportmix/loaders/dependency_check.py
reportmix/loaders/npm_audit.py
reportmix/loaders/reportmix.py
reportmix/loaders/sonarqube.py
reportmix/models/__init__.py
reportmix/models/issue.py
reportmix/models/meta.py
reportmix/models/project.py
reportmix/models/report.py
reportmix/models/severity.py
reportmix/models/subject.py
reportmix/models/tool.py
reportmix-0.6.0.dist-info/LICENSE
reportmix-0.6.0.dist-info/METADATA
reportmix-0.6.0.dist-info/WHEEL
reportmix-0.6.0.dist-info/entry_points.txt
reportmix-0.6.0.dist-info/top_level.txt
reportmix-0.6.0.dist-info/RECORD
