Metadata-Version: 2.1
Name: reportmix
Version: 0.6.0
Summary: Merge reports from multiple tools into a single file
Home-page: https://github.com/GaelGirodon/reportmix
Author: Gael Girodon
Author-email: contact@gaelgirodon.fr
License: UNKNOWN
Project-URL: Bug Reports, https://github.com/GaelGirodon/reportmix/issues
Project-URL: Source, https://github.com/GaelGirodon/reportmix
Keywords: report mix merge security dependency-check npm audit sonarqube owasp
Platform: UNKNOWN
Classifier: Development Status :: 4 - Beta
Classifier: Environment :: Console
Classifier: Intended Audience :: Developers
Classifier: License :: OSI Approved :: GNU General Public License v3 (GPLv3)
Classifier: Operating System :: OS Independent
Classifier: Programming Language :: Python :: 3
Classifier: Programming Language :: Python :: 3.8
Classifier: Topic :: Security
Classifier: Topic :: Software Development :: Quality Assurance
Requires-Python: >=3.8
Requires-Dist: requests (>=2.24.0)
Requires-Dist: jinja2 (>=2.11.2)
